pixyz/__init__.py
pixyz/utils.py
pixyz/autoregressions/__init__.py
pixyz/distributions/__init__.py
pixyz/distributions/custom_distributions.py
pixyz/distributions/distributions.py
pixyz/distributions/exponential_distributions.py
pixyz/distributions/flow_distribution.py
pixyz/distributions/mixture_distributions.py
pixyz/distributions/moe.py
pixyz/distributions/poe.py
pixyz/distributions/special_distributions.py
pixyz/flows/__init__.py
pixyz/flows/conv.py
pixyz/flows/coupling.py
pixyz/flows/flows.py
pixyz/flows/normalizations.py
pixyz/flows/normalizing_flows.py
pixyz/flows/operations.py
pixyz/layers/__init__.py
pixyz/layers/norm_util.py
pixyz/layers/resnet.py
pixyz/losses/__init__.py
pixyz/losses/adversarial_loss.py
pixyz/losses/divergences.py
pixyz/losses/elbo.py
pixyz/losses/entropy.py
pixyz/losses/iteration.py
pixyz/losses/losses.py
pixyz/losses/mmd.py
pixyz/losses/pdf.py
pixyz/losses/wasserstein.py
pixyz/models/__init__.py
pixyz/models/gan.py
pixyz/models/ml.py
pixyz/models/model.py
pixyz/models/vae.py
pixyz/models/vi.py
pixyz-0.3.3.dist-info/LICENSE
pixyz-0.3.3.dist-info/METADATA
pixyz-0.3.3.dist-info/WHEEL
pixyz-0.3.3.dist-info/top_level.txt
pixyz-0.3.3.dist-info/RECORD
