Metadata-Version: 2.1
Name: pixyz
Version: 0.3.3
Summary: Deep generative modeling library
Home-page: https://github.com/masa-su/pixyz
Author: masa-su
Author-email: masa@weblab.t.u-tokyo.ac.jp
License: MIT
Platform: UNKNOWN
Classifier: Programming Language :: Python :: 3.5
Classifier: Programming Language :: Python :: 3.6
Classifier: Programming Language :: Python :: 3.7
Classifier: License :: OSI Approved :: MIT License
Classifier: Operating System :: OS Independent
Requires-Dist: torch (>=1.0)
Requires-Dist: scipy
Requires-Dist: numpy
Requires-Dist: sympy (>=1.4)
Requires-Dist: ipython
Requires-Dist: networkx
Provides-Extra: dev
Requires-Dist: pytest ; extra == 'dev'
Requires-Dist: flake8 (==3.9.2pytest-cov) ; extra == 'dev'
Requires-Dist: pytest-flake8 ; extra == 'dev'
Requires-Dist: sphinx ; extra == 'dev'
Requires-Dist: sphinx-rtd-theme ; extra == 'dev'
Requires-Dist: twine ; extra == 'dev'
Requires-Dist: tqdm ; extra == 'dev'
Requires-Dist: torchvision ; extra == 'dev'
Requires-Dist: tensorboardX ; extra == 'dev'
Requires-Dist: sklearn ; extra == 'dev'
Provides-Extra: test
Requires-Dist: pytest-cov ; extra == 'test'
Requires-Dist: flake8 (==3.9.2) ; extra == 'test'
Requires-Dist: pytest-flake8 ; extra == 'test'
Requires-Dist: sphinx ; extra == 'test'
Requires-Dist: sphinx-rtd-theme ; extra == 'test'
Requires-Dist: tqdm ; extra == 'test'
Requires-Dist: sklearn ; extra == 'test'
